laserfields/__init__.py
laserfields/laserfields.py
laserfields-0.4.2.dist-info/licenses/LICENSE
laserfields-0.4.2.dist-info/WHEEL
laserfields-0.4.2.dist-info/METADATA
laserfields-0.4.2.dist-info/RECORD
