Metadata-Version: 2.4
Name: laserfields
Version: 0.4.2
Summary: Python library for describing time-dependent laserfields by Johannes Feist.
Author-email: Johannes Feist <johannes.feist@gmail.com>
Requires-Python: >=3.7
Classifier: License :: OSI Approved :: MIT License
License-File: LICENSE
Requires-Dist: numpy >=1.15
Requires-Dist: scipy >=1.0
Requires-Dist: numba >=0.49
Project-URL: Home, https://github.com/jfeist/pylaserfields
